django_gisserver-2.3.0.dist-info/licenses/LICENSE
gisserver/__init__.py
gisserver/compat.py
gisserver/conf.py
gisserver/crs.py
gisserver/db.py
gisserver/exceptions.py
gisserver/features.py
gisserver/geometries.py
gisserver/projection.py
gisserver/types.py
gisserver/views.py
gisserver/extensions/__init__.py
gisserver/extensions/functions.py
gisserver/extensions/queries.py
gisserver/management/__init__.py
gisserver/management/commands/__init__.py
gisserver/management/commands/loadgeojson.py
gisserver/operations/__init__.py
gisserver/operations/base.py
gisserver/operations/wfs20.py
gisserver/output/__init__.py
gisserver/output/base.py
gisserver/output/csv.py
gisserver/output/geojson.py
gisserver/output/gml32.py
gisserver/output/iters.py
gisserver/output/results.py
gisserver/output/stored.py
gisserver/output/utils.py
gisserver/output/xmlschema.py
gisserver/parsers/__init__.py
gisserver/parsers/ast.py
gisserver/parsers/query.py
gisserver/parsers/values.py
gisserver/parsers/xml.py
gisserver/parsers/fes20/__init__.py
gisserver/parsers/fes20/expressions.py
gisserver/parsers/fes20/filters.py
gisserver/parsers/fes20/identifiers.py
gisserver/parsers/fes20/lookups.py
gisserver/parsers/fes20/operators.py
gisserver/parsers/fes20/sorting.py
gisserver/parsers/gml/__init__.py
gisserver/parsers/gml/base.py
gisserver/parsers/gml/geometries.py
gisserver/parsers/ows/__init__.py
gisserver/parsers/ows/kvp.py
gisserver/parsers/ows/requests.py
gisserver/parsers/wfs20/__init__.py
gisserver/parsers/wfs20/adhoc.py
gisserver/parsers/wfs20/base.py
gisserver/parsers/wfs20/projection.py
gisserver/parsers/wfs20/requests.py
gisserver/parsers/wfs20/stored.py
gisserver/static/gisserver/bootstrap-5.3.6.min.css
gisserver/static/gisserver/index.css
gisserver/templates/gisserver/base.html
gisserver/templates/gisserver/index.html
gisserver/templates/gisserver/service_description.html
gisserver/templates/gisserver/wfs/feature_field.html
gisserver/templates/gisserver/wfs/feature_type.html
gisserver/templates/gisserver/wfs/2.0.0/get_capabilities.xml
django_gisserver-2.3.0.dist-info/METADATA
django_gisserver-2.3.0.dist-info/WHEEL
django_gisserver-2.3.0.dist-info/top_level.txt
django_gisserver-2.3.0.dist-info/RECORD
