Metadata-Version: 2.4
Name: django-gisserver
Version: 2.3.0
Summary: Django speaking WFS 2.0 (exposing GeoDjango model fields)
Home-page: https://github.com/amsterdam/django-gisserver
Author: Diederik van der Boor
Author-email: opensource@edoburu.nl
License: Mozilla Public License 2.0
Classifier: Development Status :: 5 - Production/Stable
Classifier: Environment :: Web Environment
Classifier: Intended Audience :: Developers
Classifier: License :: OSI Approved :: Mozilla Public License 2.0 (MPL 2.0)
Classifier: Operating System :: OS Independent
Classifier: Programming Language :: Python
Classifier: Programming Language :: Python :: 3.10
Classifier: Programming Language :: Python :: 3.11
Classifier: Programming Language :: Python :: 3.12
Classifier: Programming Language :: Python :: 3.13
Classifier: Programming Language :: Python :: 3.14
Classifier: Framework :: Django
Classifier: Framework :: Django :: 4.2
Classifier: Framework :: Django :: 5.2
Classifier: Topic :: Internet :: WWW/HTTP
Classifier: Topic :: Internet :: WWW/HTTP :: Dynamic Content
Classifier: Topic :: Software Development :: Libraries :: Application Frameworks
Classifier: Topic :: Software Development :: Libraries :: Python Modules
Requires: Django (>=4.2, >=5.2, <6.0)
Requires-Python: >=3.10
License-File: LICENSE
Requires-Dist: Django<6.0,>=4.2
Requires-Dist: defusedxml>=0.7.1
Requires-Dist: lru_dict>=1.4.1
Requires-Dist: orjson>=3.11.5
Requires-Dist: pyproj>=3.7.1
Provides-Extra: tests
Requires-Dist: django-environ>=0.12.0; extra == "tests"
Requires-Dist: psycopg2-binary>=2.9.11; extra == "tests"
Requires-Dist: lxml>=6.0.2; extra == "tests"
Requires-Dist: pytest>=9.0.2; extra == "tests"
Requires-Dist: pytest-django>=4.11.1; extra == "tests"
Requires-Dist: pytest-cov>=7.0.0; extra == "tests"
Provides-Extra: docs
Requires-Dist: Django~=5.2; extra == "docs"
Requires-Dist: sphinxcontrib-django>=2.5; extra == "docs"
Requires-Dist: myst-parser>=4.0.1; extra == "docs"
Requires-Dist: psycopg2-binary>=2.9.11; extra == "docs"
Dynamic: author
Dynamic: author-email
Dynamic: classifier
Dynamic: description
Dynamic: description-content-type
Dynamic: home-page
Dynamic: license
Dynamic: license-file
Dynamic: provides-extra
Dynamic: requires
Dynamic: requires-dist
Dynamic: requires-python
Dynamic: summary
